ethereumrpc/__init__.py
ethereumrpc/authproxy.py
jsonrpc/__init__.py
jsonrpc/authproxy.py
jsonrpc/json.py
jsonrpc/proxy.py
python_ethereumrpc-0.1.dist-info/LICENSE
python_ethereumrpc-0.1.dist-info/METADATA
python_ethereumrpc-0.1.dist-info/WHEEL
python_ethereumrpc-0.1.dist-info/top_level.txt
python_ethereumrpc-0.1.dist-info/RECORD
