Metadata-Version: 2.1
Name: python-ethereumrpc
Version: 0.1
Summary: Enhanced version of python-jsonrpc for use with Ethereum
Home-page: http://www.github.com/nggih/python-ethereumrpc
Author: Linggih Saputro
Author-email: <linggih.saputro@sci.ui.ac.id>
Maintainer: Linggih Saputro
Maintainer-email: <linggih.saputro@sci.ui.ac.id>
License: UNKNOWN
Platform: UNKNOWN
Classifier: License :: OSI Approved :: GNU Library or Lesser General Public License (LGPL)
Classifier: Operating System :: OS Independent
